libcosimpy/CosimAlgorithm.py
libcosimpy/CosimConstants.py
libcosimpy/CosimEnums.py
libcosimpy/CosimExecution.py
libcosimpy/CosimLibrary.py
libcosimpy/CosimLogging.py
libcosimpy/CosimManipulator.py
libcosimpy/CosimObserver.py
libcosimpy/CosimSlave.py
libcosimpy/__about__.py
libcosimpy/__init__.py
libcosimpy/_internal.py
libcosimpy/libcosimc/boost_atomic.dll
libcosimpy/libcosimc/boost_charconv.dll
libcosimpy/libcosimc/boost_chrono.dll
libcosimpy/libcosimc/boost_container.dll
libcosimpy/libcosimc/boost_context.dll
libcosimpy/libcosimc/boost_contract.dll
libcosimpy/libcosimc/boost_coroutine.dll
libcosimpy/libcosimc/boost_date_time.dll
libcosimpy/libcosimc/boost_filesystem.dll
libcosimpy/libcosimc/boost_graph.dll
libcosimpy/libcosimc/boost_iostreams.dll
libcosimpy/libcosimc/boost_json.dll
libcosimpy/libcosimc/boost_locale.dll
libcosimpy/libcosimc/boost_log.dll
libcosimpy/libcosimc/boost_log_setup.dll
libcosimpy/libcosimc/boost_math_c99.dll
libcosimpy/libcosimc/boost_math_c99f.dll
libcosimpy/libcosimc/boost_math_c99l.dll
libcosimpy/libcosimc/boost_math_tr1.dll
libcosimpy/libcosimc/boost_math_tr1f.dll
libcosimpy/libcosimc/boost_math_tr1l.dll
libcosimpy/libcosimc/boost_nowide.dll
libcosimpy/libcosimc/boost_prg_exec_monitor.dll
libcosimpy/libcosimc/boost_program_options.dll
libcosimpy/libcosimc/boost_random.dll
libcosimpy/libcosimc/boost_regex.dll
libcosimpy/libcosimc/boost_serialization.dll
libcosimpy/libcosimc/boost_stacktrace_noop.dll
libcosimpy/libcosimc/boost_stacktrace_windbg.dll
libcosimpy/libcosimc/boost_stacktrace_windbg_cached.dll
libcosimpy/libcosimc/boost_system.dll
libcosimpy/libcosimc/boost_thread.dll
libcosimpy/libcosimc/boost_timer.dll
libcosimpy/libcosimc/boost_type_erasure.dll
libcosimpy/libcosimc/boost_unit_test_framework.dll
libcosimpy/libcosimc/boost_url.dll
libcosimpy/libcosimc/boost_wave.dll
libcosimpy/libcosimc/boost_wserialization.dll
libcosimpy/libcosimc/bz2.dll
libcosimpy/libcosimc/cbor.dll
libcosimpy/libcosimc/cosim.dll
libcosimpy-0.0.3.post1.dist-info/METADATA
libcosimpy-0.0.3.post1.dist-info/WHEEL
libcosimpy-0.0.3.post1.dist-info/licenses/LICENSE
libcosimpy-0.0.3.post1.dist-info/RECORD
