Metadata-Version: 2.4
Name: libcosimpy
Version: 0.0.3.post1
Summary: Python wrapper for the libcosim library
Project-URL: Homepage, https://github.com/open-simulation-platform/libcosimpy
Author-email: Magnus Steinstø <magnus.steinsto@dnv.com>
Maintainer-email: Hee Jong Park <hee.jong.park@dnv.com>
License-File: LICENSE
Classifier: License :: OSI Approved :: Mozilla Public License 2.0 (MPL 2.0)
Classifier: Operating System :: Microsoft :: Windows
Classifier: Operating System :: POSIX :: Linux
Classifier: Programming Language :: Python :: 3 :: Only
Classifier: Programming Language :: Python :: 3.10
Classifier: Programming Language :: Python :: 3.11
Classifier: Programming Language :: Python :: 3.12
Classifier: Programming Language :: Python :: 3.13
Requires-Python: <3.14,>=3.10
